QuickMediaDL/QuickMediaDL.py
QuickMediaDL/__init__.py
quickmediadl-0.2.0.dist-info/METADATA
quickmediadl-0.2.0.dist-info/WHEEL
quickmediadl-0.2.0.dist-info/top_level.txt
quickmediadl-0.2.0.dist-info/RECORD
