Metadata-Version: 2.4
Name: QuickMediaDL
Version: 0.2.0
Summary: An advanced library for downloading video and audio from online sources
Home-page: https://github.com/Amirprx3/QuickMediaDL
Author: Amirhossein bahrami
Author-email: amirbaahrami@gmail.com
Keywords: downloader video audio youtube yt-dlp
Classifier: Programming Language :: Python :: 3
Classifier: License :: OSI Approved :: MIT License
Classifier: Operating System :: OS Independent
Classifier: Topic :: Multimedia :: Video :: Conversion
Classifier: Topic :: Software Development :: Libraries :: Python Modules
Requires-Python: >=3.7
Requires-Dist: yt-dlp
Requires-Dist: tqdm
Requires-Dist: ffmpeg-python
Dynamic: author
Dynamic: author-email
Dynamic: classifier
Dynamic: description
Dynamic: description-content-type
Dynamic: home-page
Dynamic: keywords
Dynamic: requires-dist
Dynamic: requires-python
Dynamic: summary
